{
  "url": "https://www.cloudflare.com/pl-pl/",
  "unique_key": "eca362936093e6481403ba26420b9dcd6c208b2b340c106b97804c8920654b82",
  "method": "GET",
  "headers": {
    "x-crawl-parent": "https://www.cloudflare.com?utm_source=challenge&utm_campaign=m"
  },
  "payload": null,
  "user_data": {
    "__crawlee": {
      "state": 3,
      "crawlDepth": 5
    },
    "depth": 5
  },
  "retry_count": 0,
  "no_retry": false,
  "loaded_url": "https://www.cloudflare.com/pl-pl/",
  "handled_at": "2025-10-02 00:33:28.641560+00:00",
  "id": "HFLzCgKdUikUnVv",
  "json_": "{\n  \"url\": \"https://www.cloudflare.com/pl-pl/\",\n  \"unique_key\": \"eca362936093e6481403ba26420b9dcd6c208b2b340c106b97804c8920654b82\",\n  \"method\": \"GET\",\n  \"headers\": {\n    \"x-crawl-parent\": \"https://www.cloudflare.com?utm_source=challenge&utm_campaign=m\"\n  },\n  \"payload\": null,\n  \"user_data\": {\n    \"__crawlee\": {\n      \"state\": 3,\n      \"crawlDepth\": 5\n    },\n    \"depth\": 5\n  },\n  \"retry_count\": 0,\n  \"no_retry\": false,\n  \"loaded_url\": \"https://www.cloudflare.com/pl-pl/\",\n  \"handled_at\": \"2025-10-02 00:33:28.641560+00:00\",\n  \"id\": \"HFLzCgKdUikUnVv\",\n  \"order_no\": null\n}",
  "order_no": null
}