{
  "url": "https://www.nsf.gov/shutdown",
  "unique_key": "6218d76a70d8a3f9362d89cfffea4532e6ac6801fca30d40229bc3da8f49214f",
  "method": "GET",
  "headers": {
    "x-crawl-parent": "https://www.research.gov/research-web/"
  },
  "payload": null,
  "user_data": {
    "__crawlee": {
      "crawlDepth": 5
    },
    "depth": 5
  },
  "retry_count": 0,
  "no_retry": false,
  "loaded_url": null,
  "handled_at": null,
  "id": "IAjfAoQWF2BLnnU",
  "json_": "{\n  \"url\": \"https://www.nsf.gov/shutdown\",\n  \"unique_key\": \"6218d76a70d8a3f9362d89cfffea4532e6ac6801fca30d40229bc3da8f49214f\",\n  \"method\": \"GET\",\n  \"headers\": {\n    \"x-crawl-parent\": \"https://www.research.gov/research-web/\"\n  },\n  \"payload\": null,\n  \"user_data\": {\n    \"__crawlee\": {\n      \"crawlDepth\": 5\n    },\n    \"depth\": 5\n  },\n  \"retry_count\": 0,\n  \"no_retry\": false,\n  \"loaded_url\": null,\n  \"handled_at\": null,\n  \"id\": \"IAjfAoQWF2BLnnU\",\n  \"order_no\": \"1759358729375.231981\"\n}",
  "order_no": "1759358729375.231981"
}