{
  "url": "https://par.nsf.gov#main_content",
  "unique_key": "6d96be2011ade31edaf174125beb53879bba581c9fa86c88eb1096e86054d8bc",
  "method": "GET",
  "headers": {
    "x-crawl-parent": "https://par.nsf.gov"
  },
  "payload": null,
  "user_data": {
    "__crawlee": {
      "crawlDepth": 5
    },
    "depth": 5
  },
  "retry_count": 0,
  "no_retry": false,
  "loaded_url": null,
  "handled_at": null,
  "id": "wiotvepjJCRI9TT",
  "json_": "{\n  \"url\": \"https://par.nsf.gov#main_content\",\n  \"unique_key\": \"6d96be2011ade31edaf174125beb53879bba581c9fa86c88eb1096e86054d8bc\",\n  \"method\": \"GET\",\n  \"headers\": {\n    \"x-crawl-parent\": \"https://par.nsf.gov\"\n  },\n  \"payload\": null,\n  \"user_data\": {\n    \"__crawlee\": {\n      \"crawlDepth\": 5\n    },\n    \"depth\": 5\n  },\n  \"retry_count\": 0,\n  \"no_retry\": false,\n  \"loaded_url\": null,\n  \"handled_at\": null,\n  \"id\": \"wiotvepjJCRI9TT\",\n  \"order_no\": \"1759358739277.116060\"\n}",
  "order_no": "1759358739277.116060"
}